README.md
setup.py
requests_prettyprint/__init__.py
requests_prettyprint/requests_prettyprint.py
requests_prettyprint.egg-info/PKG-INFO
requests_prettyprint.egg-info/SOURCES.txt
requests_prettyprint.egg-info/dependency_links.txt
requests_prettyprint.egg-info/top_level.txt