Metadata-Version: 1.1
Name: requests-prettyprint
Version: 0.0.3
Summary: Python Requests Pretty Printer
Home-page: https://github.com/atappert-fe/requests-prettyprint
Author: Andrew Tappert
Author-email: andrew.tappert@fireeye.com
License: UNKNOWN
Platform: UNKNOWN
Classifier: Programming Language :: Python :: 3
Classifier: License :: OSI Approved :: MIT License
Classifier: Operating System :: OS Independent
